setup.py
Simple_SysLog_Handler.egg-info/PKG-INFO
Simple_SysLog_Handler.egg-info/SOURCES.txt
Simple_SysLog_Handler.egg-info/dependency_links.txt
Simple_SysLog_Handler.egg-info/not-zip-safe
Simple_SysLog_Handler.egg-info/top_level.txt
simple_syslog_handler/__init__.py